tashwiki/__init__.py
tashwiki/builder.py
tashwiki/categories.py
tashwiki/cli.py
tashwiki/config.py
tashwiki/static/css/style.css
tashwiki/static/icons/rocks-16px.png
tashwiki/static/icons/rocks-32px.png
tashwiki/static/icons/rocks-64px.png
tashwiki/templates/base.html
tashwiki/templates/categories.html
tashwiki/templates/category.html
tashwiki/templates/page.html
tashwiki/utils.py
tashwiki/wikilinks.py
tashwiki-0.1.1.dist-info/LICENSE
tashwiki-0.1.1.dist-info/METADATA
tashwiki-0.1.1.dist-info/WHEEL
tashwiki-0.1.1.dist-info/entry_points.txt
tashwiki-0.1.1.dist-info/RECORD
